{
  "id": "cd640402-9414-454a-a4fa-4046850f81bd",
  "prevId": "30dfd928-39b2-4cc8-9308-ee6acb6fba39",
  "version": "7",
  "dialect": "postgresql",
  "tables": {
    "public.appointments": {
      "name": "appointments",
      "schema": "",
      "columns": {
        "appointment_id": {
          "name": "appointment_id",
          "type": "serial",
          "primaryKey": true,
          "notNull": true
        },
        "user_id": {
          "name": "user_id",
          "type": "integer",
          "primaryKey": false,
          "notNull": true
        },
        "doctor_id": {
          "name": "doctor_id",
          "type": "integer",
          "primaryKey": false,
          "notNull": true
        },
        "appointment_date": {
          "name": "appointment_date",
          "type": "date",
          "primaryKey": false,
          "notNull": true
        },
        "time_slot": {
          "name": "time_slot",
          "type": "time",
          "primaryKey": false,
          "notNull": true
        },
        "total_amount": {
          "name": "total_amount",
          "type": "numeric(10, 2)",
          "primaryKey": false,
          "notNull": false
        },
        "appointment_status": {
          "name": "appointment_status",
          "type": "appointment_status",
          "typeSchema": "public",
          "primaryKey": false,
          "notNull": false,
          "default": "'Pending'"
        },
        "created_at": {
          "name": "created_at",
          "type": "timestamp",
          "primaryKey": false,
          "notNull": false,
          "default": "now()"
        },
        "updated_at": {
          "name": "updated_at",
          "type": "timestamp",
          "primaryKey": false,
          "notNull": false,
          "default": "now()"
        }
      },
      "indexes": {},
      "foreignKeys": {
        "appointments_user_id_users_id_fk": {
          "name": "appointments_user_id_users_id_fk",
          "tableFrom": "appointments",
          "tableTo": "users",
          "columnsFrom": [
            "user_id"
          ],
          "columnsTo": [
            "id"
          ],
          "onDelete": "cascade",
          "onUpdate": "no action"
        },
        "appointments_doctor_id_doctors_doctor_id_fk": {
          "name": "appointments_doctor_id_doctors_doctor_id_fk",
          "tableFrom": "appointments",
          "tableTo": "doctors",
          "columnsFrom": [
            "doctor_id"
          ],
          "columnsTo": [
            "doctor_id"
          ],
          "onDelete": "no action",
          "onUpdate": "no action"
        }
      },
      "compositePrimaryKeys": {},
      "uniqueConstraints": {},
      "policies": {},
      "checkConstraints": {},
      "isRLSEnabled": false
    },
    "public.complaints": {
      "name": "complaints",
      "schema": "",
      "columns": {
        "complaint_id": {
          "name": "complaint_id",
          "type": "serial",
          "primaryKey": true,
          "notNull": true
        },
        "user_id": {
          "name": "user_id",
          "type": "integer",
          "primaryKey": false,
          "notNull": true
        },
        "related_appointment_id": {
          "name": "related_appointment_id",
          "type": "integer",
          "primaryKey": false,
          "notNull": false
        },
        "subject": {
          "name": "subject",
          "type": "varchar(100)",
          "primaryKey": false,
          "notNull": true
        },
        "description": {
          "name": "description",
          "type": "text",
          "primaryKey": false,
          "notNull": true
        },
        "complaint_status": {
          "name": "complaint_status",
          "type": "complaint_status",
          "typeSchema": "public",
          "primaryKey": false,
          "notNull": false,
          "default": "'Open'"
        },
        "created_at": {
          "name": "created_at",
          "type": "timestamp",
          "primaryKey": false,
          "notNull": false,
          "default": "now()"
        },
        "updated_at": {
          "name": "updated_at",
          "type": "timestamp",
          "primaryKey": false,
          "notNull": false,
          "default": "now()"
        }
      },
      "indexes": {},
      "foreignKeys": {
        "complaints_user_id_users_id_fk": {
          "name": "complaints_user_id_users_id_fk",
          "tableFrom": "complaints",
          "tableTo": "users",
          "columnsFrom": [
            "user_id"
          ],
          "columnsTo": [
            "id"
          ],
          "onDelete": "cascade",
          "onUpdate": "no action"
        },
        "complaints_related_appointment_id_appointments_appointment_id_fk": {
          "name": "complaints_related_appointment_id_appointments_appointment_id_fk",
          "tableFrom": "complaints",
          "tableTo": "appointments",
          "columnsFrom": [
            "related_appointment_id"
          ],
          "columnsTo": [
            "appointment_id"
          ],
          "onDelete": "cascade",
          "onUpdate": "no action"
        }
      },
      "compositePrimaryKeys": {},
      "uniqueConstraints": {},
      "policies": {},
      "checkConstraints": {},
      "isRLSEnabled": false
    },
    "public.doctors": {
      "name": "doctors",
      "schema": "",
      "columns": {
        "doctor_id": {
          "name": "doctor_id",
          "type": "integer",
          "primaryKey": true,
          "notNull": true
        },
        "specialization": {
          "name": "specialization",
          "type": "varchar(100)",
          "primaryKey": false,
          "notNull": true
        },
        "available_days": {
          "name": "available_days",
          "type": "text[]",
          "primaryKey": false,
          "notNull": false
        },
        "created_at": {
          "name": "created_at",
          "type": "timestamp",
          "primaryKey": false,
          "notNull": false,
          "default": "now()"
        },
        "updated_at": {
          "name": "updated_at",
          "type": "timestamp",
          "primaryKey": false,
          "notNull": false,
          "default": "now()"
        }
      },
      "indexes": {},
      "foreignKeys": {
        "doctors_doctor_id_users_id_fk": {
          "name": "doctors_doctor_id_users_id_fk",
          "tableFrom": "doctors",
          "tableTo": "users",
          "columnsFrom": [
            "doctor_id"
          ],
          "columnsTo": [
            "id"
          ],
          "onDelete": "cascade",
          "onUpdate": "no action"
        }
      },
      "compositePrimaryKeys": {},
      "uniqueConstraints": {},
      "policies": {},
      "checkConstraints": {},
      "isRLSEnabled": false
    },
    "public.payments": {
      "name": "payments",
      "schema": "",
      "columns": {
        "payment_id": {
          "name": "payment_id",
          "type": "serial",
          "primaryKey": true,
          "notNull": true
        },
        "appointment_id": {
          "name": "appointment_id",
          "type": "integer",
          "primaryKey": false,
          "notNull": true
        },
        "amount": {
          "name": "amount",
          "type": "numeric(10, 2)",
          "primaryKey": false,
          "notNull": true
        },
        "payment_status": {
          "name": "payment_status",
          "type": "varchar(50)",
          "primaryKey": false,
          "notNull": false
        },
        "transaction_id": {
          "name": "transaction_id",
          "type": "varchar(100)",
          "primaryKey": false,
          "notNull": false
        },
        "payment_date": {
          "name": "payment_date",
          "type": "timestamp",
          "primaryKey": false,
          "notNull": false
        },
        "created_at": {
          "name": "created_at",
          "type": "timestamp",
          "primaryKey": false,
          "notNull": false,
          "default": "now()"
        },
        "updated_at": {
          "name": "updated_at",
          "type": "timestamp",
          "primaryKey": false,
          "notNull": false,
          "default": "now()"
        }
      },
      "indexes": {},
      "foreignKeys": {
        "payments_appointment_id_appointments_appointment_id_fk": {
          "name": "payments_appointment_id_appointments_appointment_id_fk",
          "tableFrom": "payments",
          "tableTo": "appointments",
          "columnsFrom": [
            "appointment_id"
          ],
          "columnsTo": [
            "appointment_id"
          ],
          "onDelete": "cascade",
          "onUpdate": "no action"
        }
      },
      "compositePrimaryKeys": {},
      "uniqueConstraints": {},
      "policies": {},
      "checkConstraints": {},
      "isRLSEnabled": false
    },
    "public.prescriptions": {
      "name": "prescriptions",
      "schema": "",
      "columns": {
        "prescription_id": {
          "name": "prescription_id",
          "type": "serial",
          "primaryKey": true,
          "notNull": true
        },
        "appointment_id": {
          "name": "appointment_id",
          "type": "integer",
          "primaryKey": false,
          "notNull": true
        },
        "doctor_id": {
          "name": "doctor_id",
          "type": "integer",
          "primaryKey": false,
          "notNull": true
        },
        "patient_id": {
          "name": "patient_id",
          "type": "integer",
          "primaryKey": false,
          "notNull": true
        },
        "notes": {
          "name": "notes",
          "type": "text",
          "primaryKey": false,
          "notNull": true
        },
        "amount": {
          "name": "amount",
          "type": "numeric(10, 2)",
          "primaryKey": false,
          "notNull": true
        },
        "created_at": {
          "name": "created_at",
          "type": "timestamp",
          "primaryKey": false,
          "notNull": false,
          "default": "now()"
        },
        "updated_at": {
          "name": "updated_at",
          "type": "timestamp",
          "primaryKey": false,
          "notNull": false,
          "default": "now()"
        }
      },
      "indexes": {},
      "foreignKeys": {
        "prescriptions_appointment_id_appointments_appointment_id_fk": {
          "name": "prescriptions_appointment_id_appointments_appointment_id_fk",
          "tableFrom": "prescriptions",
          "tableTo": "appointments",
          "columnsFrom": [
            "appointment_id"
          ],
          "columnsTo": [
            "appointment_id"
          ],
          "onDelete": "cascade",
          "onUpdate": "no action"
        },
        "prescriptions_doctor_id_doctors_doctor_id_fk": {
          "name": "prescriptions_doctor_id_doctors_doctor_id_fk",
          "tableFrom": "prescriptions",
          "tableTo": "doctors",
          "columnsFrom": [
            "doctor_id"
          ],
          "columnsTo": [
            "doctor_id"
          ],
          "onDelete": "no action",
          "onUpdate": "no action"
        },
        "prescriptions_patient_id_users_id_fk": {
          "name": "prescriptions_patient_id_users_id_fk",
          "tableFrom": "prescriptions",
          "tableTo": "users",
          "columnsFrom": [
            "patient_id"
          ],
          "columnsTo": [
            "id"
          ],
          "onDelete": "no action",
          "onUpdate": "no action"
        }
      },
      "compositePrimaryKeys": {},
      "uniqueConstraints": {},
      "policies": {},
      "checkConstraints": {},
      "isRLSEnabled": false
    },
    "public.users": {
      "name": "users",
      "schema": "",
      "columns": {
        "id": {
          "name": "id",
          "type": "serial",
          "primaryKey": true,
          "notNull": true
        },
        "first_name": {
          "name": "first_name",
          "type": "varchar(50)",
          "primaryKey": false,
          "notNull": true
        },
        "last_name": {
          "name": "last_name",
          "type": "varchar(50)",
          "primaryKey": false,
          "notNull": true
        },
        "email": {
          "name": "email",
          "type": "varchar(100)",
          "primaryKey": false,
          "notNull": true
        },
        "password": {
          "name": "password",
          "type": "varchar(255)",
          "primaryKey": false,
          "notNull": true
        },
        "contact_phone": {
          "name": "contact_phone",
          "type": "varchar(20)",
          "primaryKey": false,
          "notNull": false
        },
        "address": {
          "name": "address",
          "type": "varchar(255)",
          "primaryKey": false,
          "notNull": false
        },
        "role": {
          "name": "role",
          "type": "role",
          "typeSchema": "public",
          "primaryKey": false,
          "notNull": false,
          "default": "'user'"
        },
        "image_url": {
          "name": "image_url",
          "type": "varchar(255)",
          "primaryKey": false,
          "notNull": false,
          "default": "'https://www.gravatar.com/avatar/00000000000000000000000000000000?d=mp&f=y'"
        },
        "is_verified": {
          "name": "is_verified",
          "type": "boolean",
          "primaryKey": false,
          "notNull": false,
          "default": false
        },
        "verification_code": {
          "name": "verification_code",
          "type": "varchar(10)",
          "primaryKey": false,
          "notNull": false
        },
        "created_at": {
          "name": "created_at",
          "type": "timestamp",
          "primaryKey": false,
          "notNull": false,
          "default": "now()"
        },
        "updated_at": {
          "name": "updated_at",
          "type": "timestamp",
          "primaryKey": false,
          "notNull": false,
          "default": "now()"
        }
      },
      "indexes": {},
      "foreignKeys": {},
      "compositePrimaryKeys": {},
      "uniqueConstraints": {
        "users_email_unique": {
          "name": "users_email_unique",
          "nullsNotDistinct": false,
          "columns": [
            "email"
          ]
        }
      },
      "policies": {},
      "checkConstraints": {},
      "isRLSEnabled": false
    }
  },
  "enums": {
    "public.appointment_status": {
      "name": "appointment_status",
      "schema": "public",
      "values": [
        "Pending",
        "Confirmed",
        "Cancelled"
      ]
    },
    "public.complaint_status": {
      "name": "complaint_status",
      "schema": "public",
      "values": [
        "Open",
        "In Progress",
        "Resolved",
        "Closed"
      ]
    },
    "public.role": {
      "name": "role",
      "schema": "public",
      "values": [
        "user",
        "admin",
        "doctor"
      ]
    }
  },
  "schemas": {},
  "sequences": {},
  "roles": {},
  "policies": {},
  "views": {},
  "_meta": {
    "columns": {},
    "schemas": {},
    "tables": {}
  }
}